keras_nalu/__init__.py
keras_nalu/nalu.py
keras_nalu/pretrained/__init__.py
keras_nalu/pretrained/model.h5
keras_nalu/pretrained/model.py
keras_nalu/pretrained/train.py
keras_nalu-1.3.0.dist-info/WHEEL
keras_nalu-1.3.0.dist-info/METADATA
keras_nalu-1.3.0.dist-info/RECORD
