Metadata-Version: 2.1
Name: keras-nalu
Version: 1.3.0
Summary: Keras implementation of a NALU layer
Home-page: https://github.com/genesant/keras-nalu
License: MIT
Keywords: keras,nalu
Author: Dennis Torres
Author-email: djtorres0@gmail.com
Requires-Python: >=3.5,<4.0
Classifier: License :: OSI Approved :: MIT License
Classifier: Programming Language :: Python :: 3
Classifier: Programming Language :: Python :: 3.5
Classifier: Programming Language :: Python :: 3.6
Classifier: Programming Language :: Python :: 3.7
Requires-Dist: keras (>=2.2,<3.0)
Project-URL: Repository, https://github.com/genesant/keras-nalu
